http_query/__init__.py
http_query/http_query.py
req_ase_automate-0.0.3.dist-info/METADATA
req_ase_automate-0.0.3.dist-info/WHEEL
req_ase_automate-0.0.3.dist-info/entry_points.txt
req_ase_automate-0.0.3.dist-info/top_level.txt
req_ase_automate-0.0.3.dist-info/RECORD
